svg_schematic.py
svg_schematic-1.3.dist-info/licenses/LICENSE
svg_schematic-1.3.dist-info/WHEEL
svg_schematic-1.3.dist-info/METADATA
svg_schematic-1.3.dist-info/RECORD
