Metadata-Version: 2.4
Name: svg_schematic
Version: 1.3
Summary: SVG schematic generator
Keywords: schematic,SVG
Author: Ken Kundert
Author-email: svg_schematic@nurdletech.com
Requires-Python: >=3.6
Classifier: Development Status :: 5 - Production/Stable
Classifier: Intended Audience :: Science/Research
Classifier: License :: OSI Approved :: GNU General Public License v3 or later (GPLv3+)
Classifier: Natural Language :: English
Classifier: Operating System :: POSIX :: Linux
Classifier: Programming Language :: Python :: 3
Classifier: Topic :: Utilities
Classifier: Topic :: Scientific/Engineering
License-File: LICENSE
Requires-Dist: svgwrite
Requires-Dist: inform
Project-URL: documentation, https://svg-schematic.readthedocs.io/en/latest/
Project-URL: repository, https://github.com/kenkundert/svg_schematic
